[
  {
    "id": 1,
    "title": "Fashe",
    "images": ["fashe", "fashe2", "fashe3", "fashe4", "fashe5", "fashe6", "fashe7"],
    "tools": ["HTML", "React JS", "JavaScript", "Tailwind CSS"]
  },
    {
    "id": 2,
    "title": "Task Manager",
    "images": ["task", "task2", "task3", "task4"],
    "tools": ["HTML", "Laravel", "Tailwind CSS", "Breeze"]
  },
    {
    "id": 3,
    "title": "Yummy",
    "images": ["yummy", "yummy2", "yummy3", "yummy4", "yummy5"],
    "tools": ["HTML", "SASS", "JavaScript", "Bootstrap"]
  },
  {
    "id": 4,
    "title": "Restaurant",
    "images": ["restaurant", "restaurant2", "restaurant3", "restaurant4", "restaurant5"],
    "tools": ["HTML", "SASS", "Bootstrap", "CSS"]
  },
  {
    "id": 5,
    "title": "Imane Portfolio",
    "images": ["imane", "imane2", "imane3"],
    "tools": ["HTML", "React JS", "Tailwind CSS"]
  },
  {
    "id": 6,
    "title": "Morocco",
    "images": ["mor", "mor2"],
    "tools": ["HTML", "CSS"]
  }
]
